examples/run.py
ragfl_memory/__init__.py
ragfl_memory/core.py
tests/test_core.py
ragfl_memory-0.1.0.dist-info/METADATA
ragfl_memory-0.1.0.dist-info/WHEEL
ragfl_memory-0.1.0.dist-info/top_level.txt
ragfl_memory-0.1.0.dist-info/RECORD
