Metadata-Version: 2.4
Name: ragfl_memory
Version: 0.1.0
Summary: RAGFL Memory
License: MIT
Project-URL: Homepage, https://github.com/oraichain/ragfl-memory
Requires-Python: >=3.8
Dynamic: requires-python
